connect_baas_db/__init__.py
connect_baas_db/connect_baas_db.py
connect_baas_db/open_yaml.py
connect_baas_db/postgres_handler.py
connect_baas_db-1.0.0.dist-info/LICENSE.txt
connect_baas_db-1.0.0.dist-info/METADATA
connect_baas_db-1.0.0.dist-info/WHEEL
connect_baas_db-1.0.0.dist-info/top_level.txt
connect_baas_db-1.0.0.dist-info/RECORD
